city_dsm/__init__.py
city_dsm/load_data.py
city_dsm/model.py
city_dsm/components/__init__.py
city_dsm/components/data_sampler.py
city_dsm/components/discriminator.py
city_dsm/components/model_config.py
city_dsm/components/multiloss.py
city_dsm/components/generator/__init__.py
city_dsm/components/generator/deeplabv3.py
city_dsm/components/generator/resnet.py
city_dsm-0.0.9.dist-info/METADATA
city_dsm-0.0.9.dist-info/WHEEL
city_dsm-0.0.9.dist-info/licenses/LICENSE
city_dsm-0.0.9.dist-info/RECORD
