Metadata-Version: 2.1
Name: city-dsm
Version: 0.0.9
Summary: A package to refine digital surface maps of cities
Project-URL: Homepage, https://github.com/jay-ng-mc/city-dsm
Project-URL: Bug Tracker, https://github.com/jay-ng-mc/city-dsm/issues
Author: Jay Ng
License:                     GNU GENERAL PUBLIC LICENSE
Classifier: License :: OSI Approved :: GNU General Public License v3 (GPLv3)
Classifier: Operating System :: OS Independent
Classifier: Programming Language :: Python :: 3
Requires-Python: >=3.8
Requires-Dist: torch>=1.12.1
Requires-Dist: torchvision>=0.13.1
Requires-Dist: typing-extensions
